CHANGES
INSTALL
LICENSE
MANIFEST.in
README.md
setup.cfg
setup.py
fdfs_client/__init__.py
fdfs_client/client.conf
fdfs_client/client.py
fdfs_client/connection.py
fdfs_client/exceptions.py
fdfs_client/fdfs_protol.py
fdfs_client/fdfs_test.py
fdfs_client/sendfilemodule.c
fdfs_client/storage_client.py
fdfs_client/tracker_client.py
fdfs_client/utils.py
fdfs_client.egg-info/PKG-INFO
fdfs_client.egg-info/SOURCES.txt
fdfs_client.egg-info/dependency_links.txt
fdfs_client.egg-info/top_level.txt