Metadata-Version: 1.1
Name: fdfs-client
Version: 4.0.7
Summary: Python client for Fastdfs ver 4.07
Home-page: UNKNOWN
Author: lmb
Author-email: luominbin@hotmail.com
License: GPLV3
Keywords: Fastdfs,Distribute File System
Platform: UNKNOWN
Classifier: Development Status :: 3 - Alpha
Classifier: Environment :: Console
Classifier: Intended Audience :: Developers
Classifier: Operating System :: OS Independent
Classifier: Programming Language :: Python
